mirjalolspeed/__init__.py
mirjalolspeed/speedtest.py
mirjalolspeed-0.1.0.dist-info/METADATA
mirjalolspeed-0.1.0.dist-info/WHEEL
mirjalolspeed-0.1.0.dist-info/top_level.txt
mirjalolspeed-0.1.0.dist-info/RECORD
