Metadata-Version: 2.4
Name: mirjalolspeed
Version: 0.1.0
Summary: Live internet speed test library by Mirjalol
Author: Mirjalol
Requires-Python: >=3.8
